typstpy/__init__.py
typstpy/_constants.py
typstpy/_core.py
typstpy/customizations.py
typstpy/document.py
typstpy/subpar.py
typstpy/std/__init__.py
typstpy/std/layout.py
typstpy/std/model.py
typstpy/std/text.py
typstpy/std/visualize.py
typstpy-1.3.0.dist-info/licenses/LICENSE.txt
typstpy-1.3.0.dist-info/METADATA
typstpy-1.3.0.dist-info/WHEEL
typstpy-1.3.0.dist-info/top_level.txt
typstpy-1.3.0.dist-info/RECORD
