Metadata-Version: 2.4
Name: typstpy
Version: 1.3.0
Summary: Python interface to generate executable Typst code.
Author-email: chenjunhan <beibingyangliuying@foxmail.com>
License-Expression: MIT
Requires-Python: >=3.10
License-File: LICENSE.txt
Requires-Dist: attrs>=25.3.0
Requires-Dist: cytoolz>=1.0.1
Requires-Dist: deprecated>=1.2.18
Dynamic: license-file
